{
  "schema_version": 1,
  "kind": "report_diff",
  "report_version": "20260721T222556Z",
  "previous_version": "20260721T122543Z",
  "generated_at": "2026-07-21T22:25:56.524438+00:00",
  "previous_generated_at": "2026-07-21T12:25:43.954727+00:00",
  "gap_hours": 10.0,
  "baseline": false,
  "schedule_id": 13,
  "watchlist_id": 6,
  "persona": "swing",
  "thresholds": {
    "conviction": 5,
    "rank_score": 3.0,
    "confirmation": 10,
    "trap_risk": 10,
    "rr": 0.3,
    "level_atr_mult": 0.25,
    "level_pct_floor": 1.0
  },
  "universe": {
    "added": [],
    "removed": [],
    "count_from": 49,
    "count_to": 49,
    "changed": false
  },
  "symbols": {
    "ALGN": {
      "status": "new",
      "reason": "new_signal",
      "verdict": {
        "to": "arm"
      },
      "snapshot": {
        "label": "S/R Breakout",
        "direction": "long",
        "verdict": "arm",
        "conviction": 46,
        "rr": 2.54
      }
    },
    "COO": {
      "status": "new",
      "reason": "new_signal",
      "verdict": {
        "to": "watch"
      },
      "snapshot": {
        "label": "S/R Bounce",
        "direction": "short",
        "verdict": "watch",
        "conviction": 69,
        "rr": 0.06
      }
    },
    "INCY": {
      "status": "new",
      "reason": "new_signal",
      "verdict": {
        "to": "arm"
      },
      "snapshot": {
        "label": "S/R Bounce",
        "direction": "short",
        "verdict": "arm",
        "conviction": 37,
        "rr": 5.13
      }
    },
    "JNJ": {
      "status": "new",
      "reason": "new_signal",
      "verdict": {
        "to": "arm"
      },
      "snapshot": {
        "label": "S/R Bounce",
        "direction": "short",
        "verdict": "arm",
        "conviction": 69,
        "rr": 3.61
      }
    },
    "MDT": {
      "status": "new",
      "reason": "new_signal",
      "verdict": {
        "to": "avoid"
      },
      "snapshot": {
        "label": "S/R Bounce",
        "direction": "short",
        "verdict": "avoid",
        "conviction": 50,
        "rr": 1.87
      }
    },
    "RMD": {
      "status": "new",
      "reason": "new_signal",
      "verdict": {
        "to": "watch"
      },
      "snapshot": {
        "label": "S/R Breakout",
        "direction": "long",
        "verdict": "watch",
        "conviction": 68,
        "rr": 1.71
      }
    },
    "TECH": {
      "status": "new",
      "reason": "new_signal",
      "verdict": {
        "to": "arm"
      },
      "snapshot": {
        "label": "S/R Bounce",
        "direction": "short",
        "verdict": "arm",
        "conviction": 41,
        "rr": 14.75
      }
    },
    "XRAY": {
      "status": "new",
      "reason": "new_signal",
      "verdict": {
        "to": "arm"
      },
      "snapshot": {
        "label": "S/R Bounce",
        "direction": "short",
        "verdict": "arm",
        "conviction": 55,
        "rr": 1.44
      }
    },
    "ABT": {
      "status": "dropped",
      "reason": "no_longer_qualifies",
      "last": {
        "verdict": "take",
        "conviction": 86,
        "age_bars": 0
      }
    },
    "BIIB": {
      "status": "dropped",
      "reason": "no_longer_qualifies",
      "last": {
        "verdict": "arm",
        "conviction": 37,
        "age_bars": 0
      }
    },
    "CNC": {
      "status": "dropped",
      "reason": "no_longer_qualifies",
      "last": {
        "verdict": "watch",
        "conviction": 93,
        "age_bars": 0
      }
    },
    "IDXX": {
      "status": "dropped",
      "reason": "no_longer_qualifies",
      "last": {
        "verdict": "watch",
        "conviction": 86,
        "age_bars": 0
      }
    },
    "UNH": {
      "status": "dropped",
      "reason": "no_longer_qualifies",
      "last": {
        "verdict": "avoid",
        "conviction": 24,
        "age_bars": 0
      }
    },
    "AMGN": {
      "status": "changed",
      "verdict": {
        "from": "take",
        "to": "watch",
        "transition": "demotion"
      },
      "conviction": {
        "from": 86,
        "to": 92,
        "delta": 6
      },
      "rank_score": {
        "from": 49.4,
        "to": 30.2,
        "delta": -19.2
      },
      "quality": {
        "trap_risk": {
          "from": 0,
          "to": 27,
          "delta": 27
        }
      },
      "plan": {
        "target": {
          "from": 392.2272,
          "to": 375.01,
          "delta": -17.2172,
          "pct": -4.73
        },
        "rr": {
          "from": 3.77,
          "to": 0.92,
          "delta": -2.85
        },
        "moved": true
      },
      "confirmation": {
        "score": {
          "from": 15,
          "to": 46,
          "delta": 31
        },
        "resolved": [
          "rejection / reclaim candle in your direction",
          "volume \u22651.2\u00d7 on the confirmation bar"
        ],
        "still_missing": [
          "reclaim the last lower-high 375.01"
        ]
      },
      "price": {
        "from": 363.97,
        "to": 366.15,
        "pct": 0.6
      },
      "derived": {
        "toward_target_pct": 0.0,
        "toward_stop_pct": -0.0
      },
      "highlights": [
        "Demoted TAKE \u2192 WATCH",
        "Trap risk 0 \u2192 27",
        "Confirmation advanced \u2014 rejection / reclaim candle in your direction satisfied",
        "R:R 3.77 \u2192 0.92"
      ]
    },
    "BDX": {
      "status": "changed",
      "conviction": {
        "from": 68,
        "to": 86,
        "delta": 18
      },
      "rank_score": {
        "from": 17.6,
        "to": 20.65,
        "delta": 3.05
      },
      "quality": {
        "trap_risk": {
          "from": 69,
          "to": 82,
          "delta": 13
        }
      },
      "plan": {
        "rr": {
          "from": 2.76,
          "to": 4.27,
          "delta": 1.51
        },
        "moved": false
      },
      "confirmation": {
        "still_missing": [
          "reclaim the last lower-high 159.37",
          "rejection / reclaim candle in your direction",
          "volume \u22651.2\u00d7 on the confirmation bar"
        ]
      },
      "price": {
        "from": 154.43,
        "to": 153.85,
        "pct": -0.38
      },
      "derived": {
        "toward_target_pct": 0.0,
        "toward_stop_pct": -0.0,
        "age_bars": {
          "from": 0,
          "to": 1
        }
      },
      "highlights": [
        "Trap risk 69 \u2192 82",
        "R:R 2.76 \u2192 4.27"
      ]
    },
    "BIO": {
      "status": "changed",
      "verdict": {
        "from": "arm",
        "to": "watch",
        "transition": "demotion"
      },
      "rank_score": {
        "from": 24.9,
        "to": 17.1,
        "delta": -7.8
      },
      "quality": {
        "grade": {
          "from": "D",
          "to": "C"
        },
        "trap_risk": {
          "from": 69,
          "to": 53,
          "delta": -16
        }
      },
      "plan": {
        "stop": {
          "from": 311.4471,
          "to": 306.4828,
          "delta": -4.9643,
          "pct": -1.64
        },
        "moved": true
      },
      "confirmation": {
        "score": {
          "from": 31,
          "to": 15,
          "delta": -16
        },
        "added_missing": [
          "rejection / reclaim candle in your direction"
        ],
        "still_missing": [
          "reclaim the last higher-low 282.0",
          "rejection / reclaim candle in your direction",
          "volume \u22651.2\u00d7 on the confirmation bar"
        ]
      },
      "price": {
        "from": 301.98,
        "to": 301.22,
        "pct": -0.25
      },
      "derived": {
        "toward_target_pct": -0.0,
        "toward_stop_pct": 0.0
      },
      "highlights": [
        "Demoted ARM \u2192 WATCH"
      ]
    },
    "BMY": {
      "status": "changed",
      "plan": {
        "entry": {
          "from": 60.18,
          "to": 60.92,
          "delta": 0.74,
          "pct": 1.23
        },
        "target": {
          "from": 63.4534,
          "to": 65.176,
          "delta": 1.7226,
          "pct": 2.86
        },
        "moved": true
      },
      "confirmation": {
        "score": {
          "from": 38,
          "to": 23,
          "delta": -15
        },
        "added_missing": [
          "pull back to support 59.24"
        ],
        "state": {
          "from": "forming",
          "to": "absent"
        },
        "still_missing": [
          "pull back to support 59.24",
          "rejection / reclaim candle in your direction",
          "volume \u22651.2\u00d7 on the confirmation bar"
        ]
      },
      "price": {
        "from": 60.18,
        "to": 60.92,
        "pct": 1.23
      },
      "derived": {
        "toward_target_pct": 0.0,
        "toward_stop_pct": -0.0
      }
    },
    "CI": {
      "status": "changed",
      "verdict": {
        "from": "watch",
        "to": "take_small",
        "transition": "promotion"
      },
      "rank_score": {
        "from": 19.2,
        "to": 29.58,
        "delta": 10.38
      },
      "quality": {
        "trap_risk": {
          "from": 0,
          "to": 43,
          "delta": 43
        }
      },
      "plan": {
        "entry": {
          "from": 283.93,
          "to": 290.44,
          "delta": 6.51,
          "pct": 2.29
        },
        "stop": {
          "from": 278.5262,
          "to": 285.5177,
          "delta": 6.9915,
          "pct": 2.46
        },
        "target": {
          "from": 304.6354,
          "to": 308.7662,
          "delta": 4.1308,
          "pct": 1.45
        },
        "moved": true
      },
      "flags_cleared": [
        "take_small_block"
      ],
      "confirmation": {
        "score": {
          "from": 31,
          "to": 15,
          "delta": -16
        },
        "added_missing": [
          "volume \u22651.2\u00d7 on the confirmation bar"
        ],
        "still_missing": [
          "reclaim the last lower-high 305.07",
          "rejection / reclaim candle in your direction",
          "volume \u22651.2\u00d7 on the confirmation bar"
        ]
      },
      "price": {
        "from": 283.93,
        "to": 290.44,
        "pct": 2.29
      },
      "derived": {
        "toward_target_pct": 0.0,
        "toward_stop_pct": -0.0,
        "age_bars": {
          "from": 0,
          "to": 1
        }
      },
      "highlights": [
        "Promoted WATCH \u2192 TAKE_SMALL",
        "Trap risk 0 \u2192 43"
      ]
    },
    "COR": {
      "status": "changed",
      "confirmation": {
        "score": {
          "from": 31,
          "to": 15,
          "delta": -16
        },
        "added_missing": [
          "rejection / reclaim candle in your direction"
        ],
        "still_missing": [
          "reclaim the last higher-low 270.07",
          "rejection / reclaim candle in your direction",
          "volume \u22651.2\u00d7 on the confirmation bar"
        ]
      },
      "price": {
        "from": 303.98,
        "to": 303.23,
        "pct": -0.25
      },
      "derived": {
        "toward_target_pct": -0.0,
        "toward_stop_pct": 0.0,
        "age_bars": {
          "from": 0,
          "to": 1
        }
      }
    },
    "DGX": {
      "status": "changed",
      "quality": {
        "grade": {
          "from": "B",
          "to": "C"
        },
        "trap_risk": {
          "from": 36,
          "to": 62,
          "delta": 26
        }
      },
      "plan": {
        "stop": {
          "from": 212.2757,
          "to": 209.7634,
          "delta": -2.5123,
          "pct": -1.21
        },
        "rr": {
          "from": 1.34,
          "to": 1.8,
          "delta": 0.46
        },
        "moved": true
      },
      "confirmation": {
        "score": {
          "from": 15,
          "to": 31,
          "delta": 16
        },
        "resolved": [
          "rejection / reclaim candle in your direction"
        ],
        "still_missing": [
          "reclaim the last higher-low 192.99",
          "volume \u22651.2\u00d7 on the confirmation bar"
        ]
      },
      "price": {
        "from": 207.47,
        "to": 206.64,
        "pct": -0.4
      },
      "derived": {
        "toward_target_pct": -0.0,
        "toward_stop_pct": 0.0,
        "age_bars": {
          "from": 0,
          "to": 1
        }
      },
      "highlights": [
        "Trap risk 36 \u2192 62",
        "Confirmation advanced \u2014 rejection / reclaim candle in your direction satisfied",
        "R:R 1.34 \u2192 1.8"
      ]
    },
    "DHR": {
      "status": "changed",
      "verdict": {
        "from": "arm",
        "to": "watch",
        "transition": "demotion"
      },
      "conviction": {
        "from": 76,
        "to": 100,
        "delta": 24
      },
      "rank_score": {
        "from": 30.5,
        "to": 25.9,
        "delta": -4.6
      },
      "quality": {
        "trap_risk": {
          "from": 22,
          "to": 0,
          "delta": -22
        }
      },
      "plan": {
        "entry": {
          "from": 201.52,
          "to": 179.06,
          "delta": -22.46,
          "pct": -11.15
        },
        "stop": {
          "from": 208.2727,
          "to": 189.4052,
          "delta": -18.8675,
          "pct": -9.36
        },
        "target": {
          "from": 192.36,
          "to": 161.6377,
          "delta": -30.7223,
          "pct": -15.25
        },
        "rr": {
          "from": 1.36,
          "to": 1.68,
          "delta": 0.32
        },
        "moved": true
      },
      "flags_added": [
        "htf_agree"
      ],
      "confirmation": {
        "score": {
          "from": 46,
          "to": 15,
          "delta": -31
        },
        "added_missing": [
          "pull back to resistance 189.18",
          "rejection / reclaim candle in your direction"
        ],
        "state": {
          "from": "forming",
          "to": "absent"
        },
        "still_missing": [
          "pull back to resistance 189.18",
          "reclaim the last higher-low 175.22",
          "rejection / reclaim candle in your direction"
        ]
      },
      "price": {
        "from": 201.52,
        "to": 179.06,
        "pct": -11.15
      },
      "derived": {
        "trigger_crossed": true,
        "toward_target_pct": -0.0,
        "toward_stop_pct": 0.0
      },
      "highlights": [
        "Demoted ARM \u2192 WATCH",
        "R:R 1.36 \u2192 1.68",
        "Price crossed the entry trigger"
      ]
    },
    "DXCM": {
      "status": "changed",
      "quality": {
        "grade": {
          "from": "D",
          "to": "C"
        },
        "trap_risk": {
          "from": 82,
          "to": 60,
          "delta": -22
        }
      },
      "plan": {
        "entry": {
          "from": 75.69,
          "to": 74.75,
          "delta": -0.94,
          "pct": -1.24
        },
        "stop": {
          "from": 73.3425,
          "to": 76.6704,
          "delta": 3.3279,
          "pct": 4.4
        },
        "target": {
          "from": 81.1811,
          "to": 73.7,
          "delta": -7.4811,
          "pct": -9.88
        },
        "rr": {
          "from": 2.34,
          "to": 0.55,
          "delta": -1.79
        },
        "moved": true
      },
      "confirmation": {
        "resolved": [
          "reclaim the last lower-high 78.83"
        ],
        "added_missing": [
          "reclaim the last higher-low 67.3"
        ],
        "still_missing": [
          "reclaim the last higher-low 67.3",
          "rejection / reclaim candle in your direction",
          "volume \u22651.2\u00d7 on the confirmation bar"
        ]
      },
      "price": {
        "from": 75.69,
        "to": 74.75,
        "pct": -1.24
      },
      "derived": {
        "trigger_crossed": true,
        "toward_target_pct": -0.0,
        "toward_stop_pct": 0.0
      },
      "highlights": [
        "Confirmation advanced \u2014 reclaim the last lower-high 78.83 satisfied",
        "R:R 2.34 \u2192 0.55",
        "Price crossed the entry trigger"
      ]
    },
    "ELV": {
      "status": "changed",
      "rank_score": {
        "from": 25.3,
        "to": 22.3,
        "delta": -3.0
      },
      "quality": {
        "grade": {
          "from": "D",
          "to": "C"
        },
        "trap_risk": {
          "from": 77,
          "to": 53,
          "delta": -24
        }
      },
      "plan": {
        "entry": {
          "from": 382.335,
          "to": 393.51,
          "delta": 11.175,
          "pct": 2.92
        },
        "stop": {
          "from": 396.8726,
          "to": 376.13,
          "delta": -20.7426,
          "pct": -5.43
        },
        "target": {
          "from": 390.5118,
          "to": 428.7889,
          "delta": 38.2771,
          "pct": 10.01
        },
        "rr": {
          "from": 0.56,
          "to": 2.03,
          "delta": 1.47
        },
        "moved": true
      },
      "flags_added": [
        "htf_agree",
        "take_small_block"
      ],
      "confirmation": {
        "score": {
          "from": 31,
          "to": 15,
          "delta": -16
        },
        "resolved": [
          "reclaim the last higher-low 381.77"
        ],
        "added_missing": [
          "reclaim the last lower-high 433.64"
        ],
        "still_missing": [
          "reclaim the last lower-high 433.64",
          "rejection / reclaim candle in your direction",
          "volume \u22651.2\u00d7 on the confirmation bar"
        ]
      },
      "price": {
        "from": 382.335,
        "to": 393.51,
        "pct": 2.92
      },
      "derived": {
        "trigger_crossed": true,
        "toward_target_pct": 0.0,
        "toward_stop_pct": -0.0
      },
      "highlights": [
        "Confirmation advanced \u2014 reclaim the last higher-low 381.77 satisfied",
        "R:R 0.56 \u2192 2.03",
        "Price crossed the entry trigger"
      ]
    },
    "EW": {
      "status": "changed",
      "quality": {
        "grade": {
          "from": "A",
          "to": "B"
        },
        "trap_risk": {
          "from": 0,
          "to": 43,
          "delta": 43
        }
      },
      "confirmation": {
        "score": {
          "from": 15,
          "to": 31,
          "delta": 16
        },
        "resolved": [
          "volume \u22651.2\u00d7 on the confirmation bar"
        ],
        "still_missing": [
          "reclaim the last higher-low 83.23",
          "rejection / reclaim candle in your direction"
        ]
      },
      "price": {
        "from": 85.03,
        "to": 84.57,
        "pct": -0.54
      },
      "derived": {
        "toward_target_pct": -0.0,
        "toward_stop_pct": 0.0,
        "age_bars": {
          "from": 0,
          "to": 1
        }
      },
      "highlights": [
        "Trap risk 0 \u2192 43",
        "Confirmation advanced \u2014 volume \u22651.2\u00d7 on the confirmation bar satisfied"
      ]
    },
    "HCA": {
      "status": "changed",
      "verdict": {
        "from": "watch",
        "to": "arm",
        "transition": "promotion"
      },
      "conviction": {
        "from": 86,
        "to": 57,
        "delta": -29
      },
      "quality": {
        "grade": {
          "from": "C",
          "to": "B"
        },
        "trap_risk": {
          "from": 62,
          "to": 27,
          "delta": -35
        }
      },
      "plan": {
        "stop": {
          "from": 390.7859,
          "to": 362.239,
          "delta": -28.5469,
          "pct": -7.71
        },
        "target": {
          "from": 343.4334,
          "to": 408.3518,
          "delta": 64.9184,
          "pct": 17.53
        },
        "rr": {
          "from": 1.32,
          "to": 3.23,
          "delta": 1.91
        },
        "moved": true
      },
      "flags_cleared": [
        "htf_agree"
      ],
      "confirmation": {
        "score": {
          "from": 31,
          "to": 46,
          "delta": 15
        },
        "resolved": [
          "reclaim the last higher-low 369.63",
          "volume \u22651.2\u00d7 on the confirmation bar"
        ],
        "added_missing": [
          "reclaim the last lower-high 428.98"
        ],
        "still_missing": [
          "reclaim the last lower-high 428.98"
        ]
      },
      "price": {
        "from": 370.38,
        "to": 373.15,
        "pct": 0.75
      },
      "derived": {
        "toward_target_pct": 0.0,
        "toward_stop_pct": -0.0
      },
      "highlights": [
        "Promoted WATCH \u2192 ARM",
        "Confirmation advanced \u2014 reclaim the last higher-low 369.63 satisfied",
        "R:R 1.32 \u2192 3.23"
      ]
    },
    "HUM": {
      "status": "changed",
      "verdict": {
        "from": "avoid",
        "to": "arm",
        "transition": "promotion"
      },
      "conviction": {
        "from": 27,
        "to": 52,
        "delta": 25
      },
      "rank_score": {
        "from": 3.5,
        "to": 18.7,
        "delta": 15.2
      },
      "plan": {
        "entry": {
          "from": 397.98,
          "to": 404.36,
          "delta": 6.38,
          "pct": 1.6
        },
        "stop": {
          "from": 419.8291,
          "to": 414.8098,
          "delta": -5.0193,
          "pct": -1.26
        },
        "target": {
          "from": 387.143,
          "to": 351.8978,
          "delta": -35.2452,
          "pct": -8.86
        },
        "rr": {
          "from": 0.5,
          "to": 5.02,
          "delta": 4.52
        },
        "moved": true
      },
      "confirmation": {
        "resolved": [
          "pull back to resistance 414.33"
        ],
        "added_missing": [
          "rejection / reclaim candle in your direction"
        ],
        "state": {
          "from": "absent",
          "to": "forming"
        },
        "still_missing": [
          "reclaim the last higher-low 353.32",
          "rejection / reclaim candle in your direction",
          "volume \u22651.2\u00d7 on the confirmation bar"
        ]
      },
      "price": {
        "from": 397.98,
        "to": 404.36,
        "pct": 1.6
      },
      "derived": {
        "toward_target_pct": -0.0,
        "toward_stop_pct": 0.0
      },
      "highlights": [
        "Promoted AVOID \u2192 ARM",
        "Confirmation advanced \u2014 pull back to resistance 414.33 satisfied",
        "R:R 0.5 \u2192 5.02"
      ]
    },
    "IQV": {
      "status": "changed",
      "verdict": {
        "from": "arm",
        "to": "avoid",
        "transition": "demotion"
      },
      "conviction": {
        "from": 55,
        "to": 50,
        "delta": -5
      },
      "rank_score": {
        "from": 19.8,
        "to": 5.8,
        "delta": -14.0
      },
      "quality": {
        "grade": {
          "from": "D",
          "to": "B"
        },
        "trap_risk": {
          "from": 69,
          "to": 36,
          "delta": -33
        }
      },
      "plan": {
        "entry": {
          "from": 203.95,
          "to": 201.37,
          "delta": -2.58,
          "pct": -1.27
        },
        "stop": {
          "from": 209.8439,
          "to": 194.6582,
          "delta": -15.1857,
          "pct": -7.45
        },
        "target": {
          "from": 197.825,
          "to": 218.0386,
          "delta": 20.2136,
          "pct": 9.91
        },
        "rr": {
          "from": 1.04,
          "to": 2.48,
          "delta": 1.44
        },
        "moved": true
      },
      "confirmation": {
        "score": {
          "from": 31,
          "to": 15,
          "delta": -16
        },
        "resolved": [
          "reclaim the last higher-low 162.44"
        ],
        "added_missing": [
          "reclaim the last lower-high 212.36",
          "rejection / reclaim candle in your direction"
        ],
        "still_missing": [
          "reclaim the last lower-high 212.36",
          "rejection / reclaim candle in your direction",
          "volume \u22651.2\u00d7 on the confirmation bar"
        ]
      },
      "price": {
        "from": 203.95,
        "to": 201.37,
        "pct": -1.27
      },
      "derived": {
        "toward_target_pct": 0.0,
        "toward_stop_pct": -0.0
      },
      "highlights": [
        "Demoted ARM \u2192 AVOID",
        "Confirmation advanced \u2014 reclaim the last higher-low 162.44 satisfied",
        "R:R 1.04 \u2192 2.48"
      ]
    },
    "ISRG": {
      "status": "changed",
      "verdict": {
        "from": "avoid",
        "to": "watch",
        "transition": "promotion"
      },
      "conviction": {
        "from": 25,
        "to": 86,
        "delta": 61
      },
      "rank_score": {
        "from": 2.9,
        "to": 25.3,
        "delta": 22.4
      },
      "plan": {
        "stop": {
          "from": 328.0174,
          "to": 401.973,
          "delta": 73.9556,
          "pct": 20.94
        },
        "target": {
          "from": 462.8419,
          "to": 301.2912,
          "delta": -161.5507,
          "pct": -45.75
        },
        "rr": {
          "from": 4.37,
          "to": 0.93,
          "delta": -3.44
        },
        "moved": true
      },
      "flags_added": [
        "htf_agree"
      ],
      "confirmation": {
        "score": {
          "from": 15,
          "to": 31,
          "delta": 16
        },
        "resolved": [
          "reach a key level",
          "reclaim the last lower-high 442.72",
          "rejection / reclaim candle in your direction"
        ],
        "added_missing": [
          "pull back to resistance 430.09",
          "reclaim the last higher-low 397.52"
        ],
        "still_missing": [
          "pull back to resistance 430.09",
          "reclaim the last higher-low 397.52"
        ]
      },
      "price": {
        "from": 353.11,
        "to": 349.94,
        "pct": -0.9
      },
      "derived": {
        "toward_target_pct": -0.0,
        "toward_stop_pct": 0.0
      },
      "highlights": [
        "Promoted AVOID \u2192 WATCH",
        "Confirmation advanced \u2014 reach a key level satisfied",
        "R:R 4.37 \u2192 0.93"
      ]
    },
    "LH": {
      "status": "changed",
      "verdict": {
        "from": "avoid",
        "to": "watch",
        "transition": "promotion"
      },
      "conviction": {
        "from": 52,
        "to": 92,
        "delta": 40
      },
      "rank_score": {
        "from": 6.8,
        "to": 22.79,
        "delta": 15.99
      },
      "plan": {
        "rr": {
          "from": 1.58,
          "to": 1.23,
          "delta": -0.35
        },
        "moved": false
      },
      "confirmation": {
        "resolved": [
          "reclaim the last higher-low 253.29"
        ],
        "added_missing": [
          "reclaim the last higher-low 263.25"
        ],
        "still_missing": [
          "reclaim the last higher-low 263.25",
          "volume \u22651.2\u00d7 on the confirmation bar"
        ]
      },
      "price": {
        "from": 281.42,
        "to": 279.345,
        "pct": -0.74
      },
      "derived": {
        "toward_target_pct": -0.0,
        "toward_stop_pct": 0.0,
        "age_bars": {
          "from": 0,
          "to": 1
        }
      },
      "highlights": [
        "Promoted AVOID \u2192 WATCH",
        "Confirmation advanced \u2014 reclaim the last higher-low 253.29 satisfied",
        "R:R 1.58 \u2192 1.23"
      ]
    },
    "LLY": {
      "status": "changed",
      "quality": {
        "grade": {
          "from": "D",
          "to": "C"
        },
        "trap_risk": {
          "from": 85,
          "to": 62,
          "delta": -23
        }
      },
      "plan": {
        "entry": {
          "from": 1146.38,
          "to": 1174.94,
          "delta": 28.56,
          "pct": 2.49
        },
        "stop": {
          "from": 1069.8552,
          "to": 1195.1369,
          "delta": 125.2817,
          "pct": 10.93
        },
        "target": {
          "from": 1219.9224,
          "to": 1120.9087,
          "delta": -99.0137,
          "pct": -8.64
        },
        "rr": {
          "from": 0.96,
          "to": 2.68,
          "delta": 1.72
        },
        "moved": true
      },
      "flags_added": [
        "take_small_block"
      ],
      "flags_cleared": [
        "htf_agree"
      ],
      "confirmation": {
        "score": {
          "from": 15,
          "to": 31,
          "delta": 16
        },
        "resolved": [
          "pull back to support 1089.85",
          "reclaim the last lower-high 1248.53"
        ],
        "added_missing": [
          "reclaim the last higher-low 1089.85",
          "volume \u22651.2\u00d7 on the confirmation bar"
        ],
        "state": {
          "from": "absent",
          "to": "forming"
        },
        "still_missing": [
          "reclaim the last higher-low 1089.85",
          "rejection / reclaim candle in your direction",
          "volume \u22651.2\u00d7 on the confirmation bar"
        ]
      },
      "price": {
        "from": 1146.38,
        "to": 1174.94,
        "pct": 2.49
      },
      "derived": {
        "toward_target_pct": -0.0,
        "toward_stop_pct": 0.0
      },
      "highlights": [
        "Confirmation advanced \u2014 pull back to support 1089.85 satisfied",
        "R:R 0.96 \u2192 2.68"
      ]
    },
    "MCK": {
      "status": "changed",
      "verdict": {
        "from": "watch",
        "to": "arm",
        "transition": "promotion"
      },
      "conviction": {
        "from": 86,
        "to": 37,
        "delta": -49
      },
      "rank_score": {
        "from": 22.3,
        "to": 11.7,
        "delta": -10.6
      },
      "quality": {
        "grade": {
          "from": "D",
          "to": "B"
        },
        "trap_risk": {
          "from": 100,
          "to": 36,
          "delta": -64
        }
      },
      "plan": {
        "stop": {
          "from": 799.779,
          "to": 856.1702,
          "delta": 56.3912,
          "pct": 6.78
        },
        "target": {
          "from": 885.6758,
          "to": 807.92,
          "delta": -77.7558,
          "pct": -9.35
        },
        "rr": {
          "from": 1.72,
          "to": 0.78,
          "delta": -0.94
        },
        "moved": true
      },
      "flags_cleared": [
        "htf_agree"
      ],
      "confirmation": {
        "resolved": [
          "pull back to support 807.92",
          "reclaim the last lower-high 823.28"
        ],
        "added_missing": [
          "reclaim the last higher-low 744.89",
          "rejection / reclaim candle in your direction"
        ],
        "state": {
          "from": "absent",
          "to": "forming"
        },
        "still_missing": [
          "reclaim the last higher-low 744.89",
          "rejection / reclaim candle in your direction",
          "volume \u22651.2\u00d7 on the confirmation bar"
        ]
      },
      "price": {
        "from": 831.4,
        "to": 829.1,
        "pct": -0.28
      },
      "derived": {
        "toward_target_pct": -0.0,
        "toward_stop_pct": 0.0
      },
      "highlights": [
        "Promoted WATCH \u2192 ARM",
        "Confirmation advanced \u2014 pull back to support 807.92 satisfied",
        "R:R 1.72 \u2192 0.78"
      ]
    },
    "MTD": {
      "status": "changed",
      "conviction": {
        "from": 68,
        "to": 86,
        "delta": 18
      },
      "rank_score": {
        "from": 17.6,
        "to": 20.65,
        "delta": 3.05
      },
      "quality": {
        "grade": {
          "from": "D",
          "to": "C"
        },
        "trap_risk": {
          "from": 77,
          "to": 53,
          "delta": -24
        }
      },
      "plan": {
        "entry": {
          "from": 1271.89,
          "to": 1298.13,
          "delta": 26.24,
          "pct": 2.06
        },
        "target": {
          "from": 1342.0037,
          "to": 1370.6316,
          "delta": 28.6279,
          "pct": 2.25
        },
        "rr": {
          "from": 3.94,
          "to": 1.57,
          "delta": -2.37
        },
        "moved": true
      },
      "confirmation": {
        "still_missing": [
          "reclaim the last lower-high 1319.24",
          "rejection / reclaim candle in your direction",
          "volume \u22651.2\u00d7 on the confirmation bar"
        ]
      },
      "price": {
        "from": 1271.89,
        "to": 1298.13,
        "pct": 2.06
      },
      "derived": {
        "toward_target_pct": 0.0,
        "toward_stop_pct": -0.0,
        "age_bars": {
          "from": 0,
          "to": 1
        }
      },
      "highlights": [
        "R:R 3.94 \u2192 1.57"
      ]
    },
    "PFE": {
      "status": "changed",
      "verdict": {
        "from": "avoid",
        "to": "watch",
        "transition": "promotion"
      },
      "conviction": {
        "from": 54,
        "to": 86,
        "delta": 32
      },
      "rank_score": {
        "from": 6.2,
        "to": 22.3,
        "delta": 16.1
      },
      "quality": {
        "grade": {
          "from": "C",
          "to": "D"
        },
        "trap_risk": {
          "from": 53,
          "to": 74,
          "delta": 21
        }
      },
      "plan": {
        "stop": {
          "from": 25.0885,
          "to": 24.5825,
          "delta": -0.506,
          "pct": -2.04
        },
        "target": {
          "from": 24.2067,
          "to": 25.9801,
          "delta": 1.7734,
          "pct": 7.17
        },
        "rr": {
          "from": 1.6,
          "to": 3.14,
          "delta": 1.54
        },
        "moved": true
      },
      "flags_cleared": [
        "htf_agree"
      ],
      "confirmation": {
        "resolved": [
          "reclaim the last higher-low 23.62"
        ],
        "added_missing": [
          "reclaim the last lower-high 24.57"
        ],
        "still_missing": [
          "reclaim the last lower-high 24.57",
          "rejection / reclaim candle in your direction",
          "volume \u22651.2\u00d7 on the confirmation bar"
        ]
      },
      "price": {
        "from": 24.75,
        "to": 24.92,
        "pct": 0.69
      },
      "derived": {
        "trigger_crossed": true,
        "toward_target_pct": 0.0,
        "toward_stop_pct": -0.0
      },
      "highlights": [
        "Promoted AVOID \u2192 WATCH",
        "Trap risk 53 \u2192 74",
        "Confirmation advanced \u2014 reclaim the last higher-low 23.62 satisfied",
        "R:R 1.6 \u2192 3.14",
        "Price crossed the entry trigger"
      ]
    },
    "PODD": {
      "status": "changed",
      "conviction": {
        "from": 46,
        "to": 37,
        "delta": -9
      },
      "plan": {
        "entry": {
          "from": 167.335,
          "to": 163.73,
          "delta": -3.605,
          "pct": -2.15
        },
        "rr": {
          "from": 3.51,
          "to": 1.48,
          "delta": -2.03
        },
        "moved": true
      },
      "confirmation": {
        "still_missing": [
          "reclaim the last higher-low 153.19",
          "rejection / reclaim candle in your direction",
          "volume \u22651.2\u00d7 on the confirmation bar"
        ]
      },
      "price": {
        "from": 167.335,
        "to": 163.73,
        "pct": -2.15
      },
      "derived": {
        "toward_target_pct": -0.0,
        "toward_stop_pct": 0.0
      },
      "highlights": [
        "R:R 3.51 \u2192 1.48"
      ]
    },
    "REGN": {
      "status": "changed",
      "verdict": {
        "from": "arm",
        "to": "watch",
        "transition": "demotion"
      },
      "conviction": {
        "from": 55,
        "to": 66,
        "delta": 11
      },
      "rank_score": {
        "from": 19.8,
        "to": 12.09,
        "delta": -7.71
      },
      "plan": {
        "rr": {
          "from": 0.22,
          "to": 0.58,
          "delta": 0.36
        },
        "moved": false
      },
      "confirmation": {
        "score": {
          "from": 31,
          "to": 15,
          "delta": -16
        },
        "added_missing": [
          "rejection / reclaim candle in your direction"
        ],
        "still_missing": [
          "reclaim the last higher-low 595.23",
          "rejection / reclaim candle in your direction",
          "volume \u22651.2\u00d7 on the confirmation bar"
        ]
      },
      "price": {
        "from": 671.98,
        "to": 675.2,
        "pct": 0.48
      },
      "derived": {
        "toward_target_pct": -0.0,
        "toward_stop_pct": 0.0,
        "age_bars": {
          "from": 0,
          "to": 1
        }
      },
      "highlights": [
        "Demoted ARM \u2192 WATCH",
        "R:R 0.22 \u2192 0.58"
      ]
    },
    "STE": {
      "status": "changed",
      "conviction": {
        "from": 86,
        "to": 69,
        "delta": -17
      },
      "plan": {
        "entry": {
          "from": 214.54,
          "to": 211.695,
          "delta": -2.845,
          "pct": -1.33
        },
        "target": {
          "from": 229.3857,
          "to": 218.575,
          "delta": -10.8107,
          "pct": -5.04
        },
        "rr": {
          "from": 2.02,
          "to": 1.52,
          "delta": -0.5
        },
        "moved": true
      },
      "flags_cleared": [
        "htf_agree"
      ],
      "confirmation": {
        "score": {
          "from": 15,
          "to": 31,
          "delta": 16
        },
        "resolved": [
          "rejection / reclaim candle in your direction"
        ],
        "still_missing": [
          "reclaim the last lower-high 218.57",
          "volume \u22651.2\u00d7 on the confirmation bar"
        ]
      },
      "price": {
        "from": 214.54,
        "to": 211.695,
        "pct": -1.33
      },
      "derived": {
        "toward_target_pct": 0.0,
        "toward_stop_pct": -0.0
      },
      "highlights": [
        "Confirmation advanced \u2014 rejection / reclaim candle in your direction satisfied",
        "R:R 2.02 \u2192 1.52"
      ]
    },
    "SYK": {
      "status": "changed",
      "rank_score": {
        "from": 20.3,
        "to": 14.21,
        "delta": -6.09
      },
      "plan": {
        "entry": {
          "from": 319.1,
          "to": 314.56,
          "delta": -4.54,
          "pct": -1.42
        },
        "stop": {
          "from": 328.604,
          "to": 320.5936,
          "delta": -8.0104,
          "pct": -2.51
        },
        "moved": true
      },
      "confirmation": {
        "score": {
          "from": 31,
          "to": 15,
          "delta": -16
        },
        "resolved": [
          "reclaim the last higher-low 309.3"
        ],
        "added_missing": [
          "reclaim the last higher-low 306.68",
          "rejection / reclaim candle in your direction"
        ],
        "still_missing": [
          "reclaim the last higher-low 306.68",
          "rejection / reclaim candle in your direction",
          "volume \u22651.2\u00d7 on the confirmation bar"
        ]
      },
      "price": {
        "from": 319.1,
        "to": 314.56,
        "pct": -1.42
      },
      "derived": {
        "trigger_crossed": true,
        "toward_target_pct": -0.0,
        "toward_stop_pct": 0.0,
        "age_bars": {
          "from": 0,
          "to": 1
        }
      },
      "highlights": [
        "Confirmation advanced \u2014 reclaim the last higher-low 309.3 satisfied",
        "Price crossed the entry trigger"
      ]
    },
    "TMO": {
      "status": "changed",
      "verdict": {
        "from": "arm",
        "to": "avoid",
        "transition": "demotion"
      },
      "conviction": {
        "from": 37,
        "to": 54,
        "delta": 17
      },
      "rank_score": {
        "from": 11.7,
        "to": 7.23,
        "delta": -4.47
      },
      "quality": {
        "grade": {
          "from": "C",
          "to": "A"
        },
        "trap_risk": {
          "from": 53,
          "to": 22,
          "delta": -31
        }
      },
      "plan": {
        "stop": {
          "from": 545.7594,
          "to": 512.1611,
          "delta": -33.5983,
          "pct": -6.38
        },
        "target": {
          "from": 519.91,
          "to": 538.405,
          "delta": 18.495,
          "pct": 3.51
        },
        "rr": {
          "from": 0.32,
          "to": 1.36,
          "delta": 1.04
        },
        "moved": true
      },
      "confirmation": {
        "score": {
          "from": 15,
          "to": 54,
          "delta": 39
        },
        "resolved": [
          "reclaim the last higher-low 457.85",
          "volume \u22651.2\u00d7 on the confirmation bar"
        ],
        "still_missing": [
          "rejection / reclaim candle in your direction"
        ]
      },
      "price": {
        "from": 526.23,
        "to": 523.27,
        "pct": -0.56
      },
      "derived": {
        "toward_target_pct": 0.0,
        "toward_stop_pct": -0.0,
        "age_bars": {
          "from": 0,
          "to": 1
        }
      },
      "highlights": [
        "Demoted ARM \u2192 AVOID",
        "Confirmation advanced \u2014 reclaim the last higher-low 457.85 satisfied",
        "R:R 0.32 \u2192 1.36"
      ]
    },
    "WAT": {
      "status": "changed",
      "verdict": {
        "from": "arm",
        "to": "take",
        "transition": "promotion"
      },
      "conviction": {
        "from": 52,
        "to": 100,
        "delta": 48
      },
      "rank_score": {
        "from": 18.7,
        "to": 62.54,
        "delta": 43.84
      },
      "quality": {
        "grade": {
          "from": "C",
          "to": "A"
        },
        "trap_risk": {
          "from": 62,
          "to": 16,
          "delta": -46
        }
      },
      "plan": {
        "entry": {
          "from": 357.35,
          "to": 367.57,
          "delta": 10.22,
          "pct": 2.86
        },
        "stop": {
          "from": 348.4278,
          "to": 361.3524,
          "delta": 12.9246,
          "pct": 3.62
        },
        "target": {
          "from": 378.3494,
          "to": 405.9338,
          "delta": 27.5844,
          "pct": 7.72
        },
        "rr": {
          "from": 2.35,
          "to": 6.17,
          "delta": 3.82
        },
        "moved": true
      },
      "confirmation": {
        "still_missing": [
          "reclaim the last lower-high 383.52",
          "rejection / reclaim candle in your direction"
        ]
      },
      "price": {
        "from": 357.35,
        "to": 367.57,
        "pct": 2.86
      },
      "derived": {
        "trigger_crossed": true,
        "toward_target_pct": 0.0,
        "toward_stop_pct": -0.0,
        "age_bars": {
          "from": 0,
          "to": 1
        }
      },
      "highlights": [
        "Promoted ARM \u2192 TAKE",
        "R:R 2.35 \u2192 6.17",
        "Price crossed the entry trigger"
      ]
    },
    "ZTS": {
      "status": "changed",
      "verdict": {
        "from": "watch",
        "to": "arm",
        "transition": "promotion"
      },
      "conviction": {
        "from": 65,
        "to": 49,
        "delta": -16
      },
      "rank_score": {
        "from": 19.2,
        "to": 15.5,
        "delta": -3.7
      },
      "quality": {
        "grade": {
          "from": "B",
          "to": "D"
        },
        "trap_risk": {
          "from": 36,
          "to": 69,
          "delta": 33
        }
      },
      "plan": {
        "entry": {
          "from": 76.21,
          "to": 75.35,
          "delta": -0.86,
          "pct": -1.13
        },
        "target": {
          "from": 82.7892,
          "to": 77.98,
          "delta": -4.8092,
          "pct": -6.31
        },
        "rr": {
          "from": 2.61,
          "to": 1.6,
          "delta": -1.01
        },
        "moved": true
      },
      "flags_cleared": [
        "take_small_block"
      ],
      "confirmation": {
        "score": {
          "from": 31,
          "to": 15,
          "delta": -16
        },
        "added_missing": [
          "volume \u22651.2\u00d7 on the confirmation bar"
        ],
        "still_missing": [
          "reclaim the last lower-high 77.98",
          "rejection / reclaim candle in your direction",
          "volume \u22651.2\u00d7 on the confirmation bar"
        ]
      },
      "price": {
        "from": 76.21,
        "to": 75.35,
        "pct": -1.13
      },
      "derived": {
        "toward_target_pct": 0.0,
        "toward_stop_pct": -0.0
      },
      "highlights": [
        "Promoted WATCH \u2192 ARM",
        "Trap risk 36 \u2192 69",
        "R:R 2.61 \u2192 1.6"
      ]
    }
  },
  "summary": {
    "candidates_from": 32,
    "candidates_to": 35,
    "new": 8,
    "dropped": 5,
    "persisted": 27,
    "changed": 27,
    "unchanged": 0,
    "promotions": 9,
    "demotions": 6,
    "new_takes": [
      "CI",
      "WAT"
    ],
    "lost_takes": [
      "ABT",
      "AMGN"
    ],
    "by_verdict_from": {
      "take": 2,
      "arm": 9,
      "watch": 14,
      "avoid": 7
    },
    "by_verdict_to": {
      "take": 1,
      "take_small": 1,
      "watch": 17,
      "arm": 11,
      "avoid": 5
    },
    "material": true
  },
  "highlights": [
    {
      "rank": 1,
      "kind": "new_take",
      "symbol": "CI",
      "text": "CI became TAKE \u2014 the actionable event"
    },
    {
      "rank": 2,
      "kind": "new_take",
      "symbol": "WAT",
      "text": "WAT became TAKE \u2014 the actionable event"
    },
    {
      "rank": 3,
      "kind": "lost_take",
      "symbol": "ABT",
      "text": "ABT lost its TAKE"
    },
    {
      "rank": 4,
      "kind": "lost_take",
      "symbol": "AMGN",
      "text": "AMGN lost its TAKE"
    },
    {
      "rank": 5,
      "kind": "promotion",
      "symbol": "HCA",
      "text": "HCA promoted WATCH \u2192 ARM"
    },
    {
      "rank": 6,
      "kind": "promotion",
      "symbol": "HUM",
      "text": "HUM promoted AVOID \u2192 ARM"
    },
    {
      "rank": 7,
      "kind": "promotion",
      "symbol": "ISRG",
      "text": "ISRG promoted AVOID \u2192 WATCH"
    },
    {
      "rank": 8,
      "kind": "promotion",
      "symbol": "LH",
      "text": "LH promoted AVOID \u2192 WATCH"
    },
    {
      "rank": 9,
      "kind": "promotion",
      "symbol": "MCK",
      "text": "MCK promoted WATCH \u2192 ARM"
    },
    {
      "rank": 10,
      "kind": "promotion",
      "symbol": "PFE",
      "text": "PFE promoted AVOID \u2192 WATCH"
    },
    {
      "rank": 11,
      "kind": "promotion",
      "symbol": "ZTS",
      "text": "ZTS promoted WATCH \u2192 ARM"
    },
    {
      "rank": 12,
      "kind": "demotion",
      "symbol": "BIO",
      "text": "BIO demoted ARM \u2192 WATCH"
    },
    {
      "rank": 13,
      "kind": "demotion",
      "symbol": "DHR",
      "text": "DHR demoted ARM \u2192 WATCH"
    },
    {
      "rank": 14,
      "kind": "demotion",
      "symbol": "IQV",
      "text": "IQV demoted ARM \u2192 AVOID"
    },
    {
      "rank": 15,
      "kind": "demotion",
      "symbol": "REGN",
      "text": "REGN demoted ARM \u2192 WATCH"
    }
  ]
}